ravix/__init__.py
ravix/_version.py
ravix/_internal/__init__.py
ravix/_internal/helpers.py
ravix/data/Airbnb.csv
ravix/data/Betas.csv
ravix/data/Charges.csv
ravix/data/CustomersInsurance.csv
ravix/data/Employment.csv
ravix/data/HR_retention.csv
ravix/data/HousePrices.csv
ravix/data/JobChanges.csv
ravix/data/LoanDefault.csv
ravix/data/MarketingToys.csv
ravix/data/PriceSize.csv
ravix/data/Sales.csv
ravix/data/SalesAds.csv
ravix/data/TireSales.csv
ravix/data/Top200.csv
ravix/data/Twitter.csv
ravix/data/Vacation.csv
ravix/data/Youtube.csv
ravix/data/__init__.py
ravix/data/salary_churn.csv
ravix/diagnostics/__init__.py
ravix/diagnostics/multicollinearity.py
ravix/diagnostics/normality.py
ravix/diagnostics/variance.py
ravix/modeling/__init__.py
ravix/modeling/bsr.py
ravix/modeling/environment.py
ravix/modeling/fit.py
ravix/modeling/format_utils.py
ravix/modeling/intervals.py
ravix/modeling/parse_formula.py
ravix/modeling/predict.py
ravix/modeling/print_anova_table.py
ravix/modeling/stepwise.py
ravix/modeling/summary.py
ravix/modeling/xy_split.py
ravix/plots/__init__.py
ravix/plots/_utils.py
ravix/plots/abline.py
ravix/plots/barplot.py
ravix/plots/boxplot.py
ravix/plots/hist.py
ravix/plots/plot.py
ravix/plots/plot_bsr.py
ravix/plots/plot_cook.py
ravix/plots/plot_cor.py
ravix/plots/plot_intervals.py
ravix/plots/qq.py
ravix/plots/viz.py
ravix/transforms/__init__.py
ravix/transforms/box_cox.py
ravix-0.1.1.dist-info/licenses/LICENSE
ravix-0.1.1.dist-info/METADATA
ravix-0.1.1.dist-info/WHEEL
ravix-0.1.1.dist-info/top_level.txt
ravix-0.1.1.dist-info/RECORD
