Metadata-Version: 2.4
Name: ravix
Version: 0.1.1
Summary: Applied regression modeling and visualization for business analytics
Home-page: https://github.com/danmcgib/ravix
Author: Daniel McGibney
Author-email: dmcgibney@bus.miami.edu
License: MIT
Project-URL: Homepage, https://github.com/danielmcgibney/ravix
Project-URL: Source, https://github.com/danielmcgibney/ravix
Project-URL: Issues, https://github.com/danielmcgibney/ravix/issues
Keywords: regression,ols,logistic regression,business analytics,statistics,education,formula
Classifier: Programming Language :: Python :: 3
Classifier: Programming Language :: Python :: 3 :: Only
Classifier: License :: OSI Approved :: MIT License
Classifier: Intended Audience :: Education
Classifier: Intended Audience :: Science/Research
Classifier: Topic :: Scientific/Engineering :: Mathematics
Classifier: Topic :: Scientific/Engineering :: Information Analysis
Requires-Python: >=3.9
License-File: LICENSE
Requires-Dist: numpy>=1.20
Requires-Dist: pandas>=1.4
Requires-Dist: statsmodels>=0.13
Requires-Dist: matplotlib>=3.5
Requires-Dist: lxml
Dynamic: license-file
